oil_consumption_model/__init__.py
oil_consumption_model/oil_consumption_model.py
oil_consumption-0.1.0.dist-info/LICENSE
oil_consumption-0.1.0.dist-info/METADATA
oil_consumption-0.1.0.dist-info/WHEEL
oil_consumption-0.1.0.dist-info/top_level.txt
oil_consumption-0.1.0.dist-info/RECORD
