Metadata-Version: 2.1
Name: oil_consumption
Version: 0.1.0
Summary: A library to calculate oil consumption based on ship speed, wind speed, and sea wave height.
Author: Zesheng Jing
Author-email: 394050399@qq.com
Classifier: Programming Language :: Python :: 3
Classifier: License :: OSI Approved :: MIT License
Classifier: Operating System :: OS Independent
License-File: LICENSE
Requires-Dist: numpy
Requires-Dist: scipy
